pinhole_distance/__init__.py
pinhole_distance/classes.py
pinhole_distance/fake_flat.py
pinhole_distance/ov5647.py
pinhole_distance/rpi_cam_2.py
pinhole_distance/usb_pinhole.py
pinhole_distance-0.1.3.dist-info/LICENSE
pinhole_distance-0.1.3.dist-info/METADATA
pinhole_distance-0.1.3.dist-info/WHEEL
pinhole_distance-0.1.3.dist-info/RECORD
