Metadata-Version: 2.3
Name: pinhole-distance
Version: 0.1.3
Summary: A Python library for object distance calculations in images using pinhole projection.
License: MIT
Author: Michael Torres
Requires-Python: >=3.7
Classifier: License :: OSI Approved :: MIT License
Classifier: Programming Language :: Python :: 3
Classifier: Programming Language :: Python :: 3.7
Classifier: Programming Language :: Python :: 3.8
Classifier: Programming Language :: Python :: 3.9
Classifier: Programming Language :: Python :: 3.10
Classifier: Programming Language :: Python :: 3.11
Classifier: Programming Language :: Python :: 3.12
Classifier: Programming Language :: Python :: 3.13
Project-URL: Homepage, https://github.com/micrictor/pinhole-distance
Project-URL: Repository, https://github.com/micrictor/pinhole-distance
